LICENSE
MANIFEST.in
Makefile
README.rst
manage.py
setup.py
tox.ini
cpucoolerchart/__init__.py
cpucoolerchart/_compat.py
cpucoolerchart/app.py
cpucoolerchart/cache.py
cpucoolerchart/command.py
cpucoolerchart/crawler.py
cpucoolerchart/crawler_data.py
cpucoolerchart/extensions.py
cpucoolerchart/models.py
cpucoolerchart/views.py
cpucoolerchart/wsgi.py
cpucoolerchart.egg-info/PKG-INFO
cpucoolerchart.egg-info/SOURCES.txt
cpucoolerchart.egg-info/dependency_links.txt
cpucoolerchart.egg-info/entry_points.txt
cpucoolerchart.egg-info/requires.txt
cpucoolerchart.egg-info/top_level.txt
tests/__init__.py
tests/cache_test.py
tests/command_test.py
tests/conftest.py
tests/crawler_test.py
tests/models_test.py
tests/views_test.py
tests/data/coolenjoy_dd=1_test=1.html
tests/data/coolenjoy_dd=1_test=2.html
tests/data/coolenjoy_dd=1_test=3.html
tests/data/coolenjoy_dd=1_test=4.html
tests/data/coolenjoy_dd=2_test=1.html
tests/data/coolenjoy_dd=2_test=2.html
tests/data/coolenjoy_dd=2_test=3.html
tests/data/coolenjoy_dd=2_test=4.html
tests/data/coolenjoy_dd=3_test=1.html
tests/data/coolenjoy_dd=3_test=2.html
tests/data/coolenjoy_dd=3_test=3.html
tests/data/coolenjoy_dd=4_test=1.html
tests/data/coolenjoy_dd=4_test=2.html
tests/data/coolenjoy_dd=4_test=3.html
tests/data/mock.csv
tests/data/mock.tsv