Metadata-Version: 1.1
Name: cpucoolerchart
Version: 0.1.dev2
Summary: CPU cooler performance and price database
Home-page: https://github.com/clee704/cpucoolerchart
Author: Choongmin Lee
Author-email: choongmin@me.com
License: MIT
Keywords: cpu heatsink cooler performance price database
Platform: UNKNOWN
Classifier: Development Status :: 3 - Alpha
Classifier: Environment :: Web Environment
Classifier: Framework :: Flask
Classifier: Intended Audience :: Developers
Classifier: License :: OSI Approved :: MIT License
Classifier: Operating System :: OS Independent
Classifier: Programming Language :: Python :: 2.6
Classifier: Programming Language :: Python :: 2.7
Classifier: Programming Language :: Python :: 3.3
Classifier: Programming Language :: Python :: Implementation :: CPython
Classifier: Topic :: Communications
Classifier: Topic :: Internet :: WWW/HTTP :: Dynamic Content
Classifier: Topic :: Internet :: WWW/HTTP :: WSGI :: Application
